kickapi/__init__.py
kickapi/category_data.py
kickapi/channel_data.py
kickapi/chat_data.py
kickapi/clip_data.py
kickapi/kickapi.py
kickapi/leaderboard_data.py
kickapi/video_data.py
kickapi-0.3.6.dist-info/licenses/LICENSE
kickapi-0.3.6.dist-info/METADATA
kickapi-0.3.6.dist-info/WHEEL
kickapi-0.3.6.dist-info/top_level.txt
kickapi-0.3.6.dist-info/RECORD
