Metadata-Version: 2.4
Name: KickApi
Version: 0.3.6
Summary: A Python package for interacting with the Kick API to retrieve channel and video data.
Home-page: https://github.com/Enmn/KickApi
Author: Enmn
License: MIT
Keywords: kick,api,kickapi,live streaming,kick.com,video api,streaming platform,python kick sdk,kick bot,kick integration
License-File: LICENSE
Requires-Dist: cloudscraper
Requires-Dist: ua-generator
Dynamic: author
Dynamic: description
Dynamic: description-content-type
Dynamic: home-page
Dynamic: keywords
Dynamic: license
Dynamic: license-file
Dynamic: requires-dist
Dynamic: summary
